{
    "companies": [
        {
            "name": "Google Company",
            "address": "123 Innovation Drive, Tech City, TC 45678",
            "phone": "(123) 456-7890",
            "website": "https://www.google.com",
            "image": "images/google-1-1.svg",
            "membershipLevel": "3 - Gold",
            "networth": "$500,000"
        }, 

        {
            "name": "Apple Company",
            "address": "105 Danny Avenue, Tech World, TC 45378",
            "phone": "(+234) 704-204-2847",
            "website": "https://www.apple.com",
            "image": "images/apple-13.svg",
            "membershipLevel": "1 - Member",
            "networth": "$1,000,000"
        },

        {
            "name": "Microsoft Company",
            "address": "123 Innovation Drive, Tech City, TC 45678",
            "phone": "(123) 456-7890",
            "website": "https://www.microsoft.com",
            "image": "images/microsoft-5.svg",
            "membershipLevel": "1 - Member",
            "networth": "$250,000"
        },

        {
            "name": "Amazon Company",
            "address": "123 Innovation Drive, Tech City, TC 45678",
            "phone": "(123) 456-7890",
            "website": "https://www.amazon.com",
            "image": "images/logo-amazon.svg",
            "membershipLevel": "2- Silver",
            "networth": "$300,000"
        },

        {
            "name": "Facebook (Meta) Company",
            "address": "123 Innovation Drive, Tech City, TC 45678",
            "phone": "(123) 456-7890",
            "website": "https://www.meta.com",
            "image": "images/facebook-3-2.svg",
            "membershipLevel": "3 = Gold",
            "networth": "$500,000"
        },

        {
            "name": "Netflix Company",
            "address": "123 Innovation Drive, Tech City, TC 45678",
            "phone": "(123) 456-7890",
            "website": "https://www.netflix.com",
            "image": "images/netflix-logo-icon.svg",
            "membershipLevel": "2 = Silver",
            "networth": "$150,000"
        },

        {
            "name": "Tesla Company",
            "address": "123 Innovation Drive, Tech City, TC 45678",
            "phone": "(123) 456-7890",
            "website": "https://www.tesla.com",
            "image": "images/tesla-motors.svg",
            "membershipLevel": "3 = Gold",
            "networth": "$100,000"
        }
    ]
}